tekleo_common_utils_ai/__init__.py
tekleo_common_utils_ai/utils_dataset_coco.py
tekleo_common_utils_ai/utils_dataset_google.py
tekleo_common_utils_ai/utils_dataset_labelme.py
tekleo_common_utils_ai/utils_dataset_pascalvoc.py
tekleo_common_utils_ai/utils_detectron_model.py
tekleo_common_utils_ai/utils_visualize_facial.py
tekleo_common_utils_ai/utils_visualize_od.py
tekleo_common_utils_ai/dataset_modification/__init__.py
tekleo_common_utils_ai/dataset_modification/abstract_dataset_modifier.py
tekleo_common_utils_ai/dataset_modification/dataset_modification_pipe.py
tekleo_common_utils_ai/dataset_modification/dataset_modifier_blur.py
tekleo_common_utils_ai/dataset_modification/dataset_modifier_border.py
tekleo_common_utils_ai/dataset_modification/dataset_modifier_brightness.py
tekleo_common_utils_ai/dataset_modification/dataset_modifier_contrast.py
tekleo_common_utils_ai/dataset_modification/dataset_modifier_crop.py
tekleo_common_utils_ai/dataset_modification/dataset_modifier_flip.py
tekleo_common_utils_ai/dataset_modification/dataset_modifier_hue.py
tekleo_common_utils_ai/dataset_modification/dataset_modifier_saturation.py
tekleo_common_utils_ai/dataset_modification/dataset_modifier_sharpen.py
tekleo_common_utils_ai/test_utils_dataset_google/__init__.py
tekleo_common_utils_ai/test_utils_dataset_google/test_utils_dataset_google.py
tekleo_common_utils_ai/test_utils_dataset_labelme/__init__.py
tekleo_common_utils_ai/test_utils_dataset_labelme/test_utils_dataset_labelme.py
tekleo_common_utils_ai-0.0.0.7.dist-info/LICENSE.txt
tekleo_common_utils_ai-0.0.0.7.dist-info/METADATA
tekleo_common_utils_ai-0.0.0.7.dist-info/WHEEL
tekleo_common_utils_ai-0.0.0.7.dist-info/top_level.txt
tekleo_common_utils_ai-0.0.0.7.dist-info/RECORD
