Metadata-Version: 2.1
Name: tekleo-common-utils-ai
Version: 0.0.0.7
Summary: UNKNOWN
Home-page: https://github.com/jpleorx/tekleo-common-utils-ai
Author: Leo Ertuna
Author-email: leo.ertuna@gmail.com
License: Creative Commons Attribution-NonCommercial-NoDerivatives 4.0 International Public License
Download-URL: https://pypi.org/project/tekleo-common-utils-ai/
Platform: UNKNOWN
Requires-Dist: tekleo-common-message-protocol
Requires-Dist: tekleo-common-utils
Requires-Dist: labelme
Requires-Dist: pycocotools
Requires-Dist: imgviz
